nbclassic/__init__.py
nbclassic/__main__.py
nbclassic/_sysinfo.py
nbclassic/_version.py
nbclassic/config_manager.py
nbclassic/extensions.py
nbclassic/jstest.py
nbclassic/nbextensions.py
nbclassic/notebookapp.py
nbclassic/serverextensions.py
nbclassic/shim.py
nbclassic/shim_notebook.py
nbclassic/traits.py
nbclassic/transutils.py
nbclassic/bundler/__init__.py
nbclassic/bundler/__main__.py
nbclassic/bundler/bundlerextensions.py
nbclassic/bundler/handlers.py
nbclassic/bundler/tarball_bundler.py
nbclassic/bundler/tools.py
nbclassic/bundler/zip_bundler.py
nbclassic/bundler/tests/__init__.py
nbclassic/bundler/tests/test_bundler_api.py
nbclassic/bundler/tests/test_bundler_tools.py
nbclassic/bundler/tests/test_bundlerextension.py
nbclassic/bundler/tests/resources/empty.ipynb
nbclassic/bundler/tests/resources/another_subdir/test_file.txt
nbclassic/bundler/tests/resources/subdir/test_file.txt
nbclassic/bundler/tests/resources/subdir/subsubdir/.gitkeep
nbclassic/edit/__init__.py
nbclassic/edit/handlers.py
nbclassic/i18n/__init__.py
nbclassic/i18n/fr_FR/LC_MESSAGES/nbclassic.mo
nbclassic/i18n/fr_FR/LC_MESSAGES/nbclassic.po
nbclassic/i18n/fr_FR/LC_MESSAGES/nbjs.json
nbclassic/i18n/fr_FR/LC_MESSAGES/nbjs.po
nbclassic/i18n/fr_FR/LC_MESSAGES/nbui.mo
nbclassic/i18n/fr_FR/LC_MESSAGES/nbui.po
nbclassic/i18n/ja_JP/LC_MESSAGES/nbclassic.mo
nbclassic/i18n/ja_JP/LC_MESSAGES/nbclassic.po
nbclassic/i18n/ja_JP/LC_MESSAGES/nbjs.json
nbclassic/i18n/ja_JP/LC_MESSAGES/nbjs.po
nbclassic/i18n/ja_JP/LC_MESSAGES/nbui.mo
nbclassic/i18n/ja_JP/LC_MESSAGES/nbui.po
nbclassic/i18n/nl/LC_MESSAGES/nbclassic.mo
nbclassic/i18n/nl/LC_MESSAGES/nbclassic.po
nbclassic/i18n/nl/LC_MESSAGES/nbjs.json
nbclassic/i18n/nl/LC_MESSAGES/nbjs.po
nbclassic/i18n/nl/LC_MESSAGES/nbui.mo
nbclassic/i18n/nl/LC_MESSAGES/nbui.po
nbclassic/i18n/ru_RU/LC_MESSAGES/nbclassic.mo
nbclassic/i18n/ru_RU/LC_MESSAGES/nbclassic.po
nbclassic/i18n/ru_RU/LC_MESSAGES/nbjs.json
nbclassic/i18n/ru_RU/LC_MESSAGES/nbjs.po
nbclassic-1.1.0.dist-info/LICENSE
nbclassic-1.1.0.dist-info/METADATA
nbclassic-1.1.0.dist-info/WHEEL
nbclassic-1.1.0.dist-info/entry_points.txt
nbclassic-1.1.0.dist-info/top_level.txt
nbclassic-1.1.0.dist-info/RECORD
