Metadata-Version: 2.1
Name: nbclassic
Version: 1.1.0
Summary: Jupyter Notebook as a Jupyter Server extension.
Home-page: https://github.com/jupyter/nbclassic
Author: Jupyter Development Team
Author-email: jupyter@googlegroups.com
License: BSD-3-Clause
Keywords: ipython,jupyter,interactive,interpreter,shell,web
Platform: Linux
Platform: Mac OS X
Platform: Windows
Classifier: Intended Audience :: Developers
Classifier: Intended Audience :: System Administrators
Classifier: Intended Audience :: Science/Research
Classifier: License :: OSI Approved :: BSD License
Classifier: Programming Language :: Python
Classifier: Programming Language :: Python :: 3.7
Classifier: Programming Language :: Python :: 3.8
Classifier: Programming Language :: Python :: 3.9
Classifier: Programming Language :: Python :: 3.10
Requires-Python: >=3.7
License-File: LICENSE
Requires-Dist: ipython_genutils
Requires-Dist: notebook_shim>=0.2.3
Requires-Dist: nest-asyncio>=1.5
Requires-Dist: ipykernel
Provides-Extra: test
Requires-Dist: pytest; extra == "test"
Requires-Dist: coverage; extra == "test"
Requires-Dist: requests; extra == "test"
Requires-Dist: testpath; extra == "test"
Requires-Dist: nbval; extra == "test"
Requires-Dist: pytest-playwright; extra == "test"
Requires-Dist: pytest-cov; extra == "test"
Requires-Dist: pytest_jupyter; extra == "test"
Requires-Dist: pytest_tornasync; extra == "test"
Requires-Dist: requests-unixsocket; sys_platform != "win32" and extra == "test"
Provides-Extra: docs
Requires-Dist: sphinx; extra == "docs"
Requires-Dist: nbsphinx; extra == "docs"
Requires-Dist: sphinxcontrib_github_alt; extra == "docs"
Requires-Dist: sphinx_rtd_theme; extra == "docs"
Requires-Dist: myst-parser; extra == "docs"
Provides-Extra: json-logging
Requires-Dist: json-logging; extra == "json-logging"
